willowavif/AvifPlugin.py
willowavif/__init__.py
willowavif-0.1.3.dist-info/LICENSE
willowavif-0.1.3.dist-info/METADATA
willowavif-0.1.3.dist-info/WHEEL
willowavif-0.1.3.dist-info/top_level.txt
willowavif-0.1.3.dist-info/RECORD
